AUTHORS.rst
CONTRIBUTING.rst
LICENSE
MANIFEST.in
README.rst
setup.cfg
setup.py
djangocms_embed/__init__.py
djangocms_embed/cms_plugins.py
djangocms_embed/conf.py
djangocms_embed/models.py
djangocms_embed.egg-info/PKG-INFO
djangocms_embed.egg-info/SOURCES.txt
djangocms_embed.egg-info/dependency_links.txt
djangocms_embed.egg-info/not-zip-safe
djangocms_embed.egg-info/requires.txt
djangocms_embed.egg-info/top_level.txt
djangocms_embed/migrations/0001_initial.py
djangocms_embed/migrations/__init__.py
djangocms_embed/static/css/djangocms_embed/djangocms_embed.css
djangocms_embed/static/js/djangocms_embed/djangocms_embed.js
djangocms_embed/templates/djangocms_embed/default.html